{
    "Ar36": {
        "error": 0.000591361945810384,
        "error_type": "SEM",
        "filter_outliers_dict": {
            "filter_outliers": true,
            "iterations": 1,
            "std_devs": 2,
            "use_iqr_filtering": false,
            "use_standard_deviation_filtering": false
        },
        "fit": "Linear",
        "fn": 117,
        "include_baseline_error": false,
        "n": 120,
        "outlier_excluded": [
            105,
            28,
            45
        ],
        "reviewed": true,
        "user_excluded": [],
        "value": 0.048648096717071654
    },
    "Ar37": {
        "error": 0.0063233136310912414,
        "error_type": "SEM",
        "filter_outliers_dict": {
            "filter_outliers": true,
            "iterations": 1,
            "std_devs": 2,
            "use_iqr_filtering": false,
            "use_standard_deviation_filtering": false
        },
        "fit": "Linear",
        "fn": 114,
        "include_baseline_error": false,
        "n": 120,
        "outlier_excluded": [
            0,
            1,
            101,
            52,
            56,
            27
        ],
        "reviewed": true,
        "user_excluded": [],
        "value": 0.03384878887072024
    },
    "Ar38": {
        "error": 0.004985639674169873,
        "error_type": "SEM",
        "filter_outliers_dict": {
            "filter_outliers": true,
            "iterations": 1,
            "std_devs": 2,
            "use_iqr_filtering": false,
            "use_standard_deviation_filtering": false
        },
        "fit": "Linear",
        "fn": 117,
        "include_baseline_error": false,
        "n": 120,
        "outlier_excluded": [
            0,
            1,
            2
        ],
        "reviewed": true,
        "user_excluded": [],
        "value": 0.186798533244588
    },
    "Ar39": {
        "error": 0.01286380013034643,
        "error_type": "SEM",
        "filter_outliers_dict": {
            "filter_outliers": true,
            "iterations": 1,
            "std_devs": 2,
            "use_iqr_filtering": false,
            "use_standard_deviation_filtering": false
        },
        "fit": "Linear",
        "fn": 117,
        "include_baseline_error": false,
        "n": 120,
        "outlier_excluded": [
            0,
            1,
            17
        ],
        "reviewed": true,
        "user_excluded": [],
        "value": 11.998342408745547
    },
    "Ar40": {
        "error": 0.09071578114550409,
        "error_type": "SEM",
        "filter_outliers_dict": {
            "filter_outliers": true,
            "iterations": 1,
            "std_devs": 2,
            "use_iqr_filtering": false,
            "use_standard_deviation_filtering": false
        },
        "fit": "Linear",
        "fn": 114,
        "include_baseline_error": false,
        "n": 120,
        "outlier_excluded": [
            1,
            100,
            70,
            41,
            79,
            52
        ],
        "reviewed": true,
        "user_excluded": [],
        "value": 2043.6889731406654
    },
    "Ar41": {
        "error": 0.02723611645142426,
        "error_type": "SEM",
        "filter_outliers_dict": {
            "filter_outliers": true,
            "iterations": 1,
            "std_devs": 2
        },
        "fit": "Average",
        "value": -0.33463985186897877
    }
}