{
    "Ar36": {
        "error": 0.00035157510010720407,
        "error_type": "SEM",
        "filter_outliers_dict": {
            "filter_outliers": true,
            "iterations": 1,
            "std_devs": 3,
            "use_iqr_filtering": false,
            "use_standard_deviation_filtering": false
        },
        "fit": "Linear",
        "fn": 119,
        "include_baseline_error": true,
        "n": 120,
        "outlier_excluded": [
            0
        ],
        "reviewed": true,
        "user_excluded": [],
        "value": 0.012607896091134187
    },
    "Ar37": {
        "error": 0.006943280422919287,
        "error_type": "SEM",
        "filter_outliers_dict": {
            "filter_outliers": true,
            "iterations": 1,
            "std_devs": 3,
            "use_iqr_filtering": false,
            "use_standard_deviation_filtering": false
        },
        "fit": "Linear",
        "fn": 118,
        "include_baseline_error": true,
        "n": 120,
        "outlier_excluded": [
            0,
            1
        ],
        "reviewed": true,
        "user_excluded": [],
        "value": 0.0334889888960198
    },
    "Ar38": {
        "error": 0.0068131956937155,
        "error_type": "SEM",
        "filter_outliers_dict": {
            "filter_outliers": true,
            "iterations": 1,
            "std_devs": 3,
            "use_iqr_filtering": false,
            "use_standard_deviation_filtering": false
        },
        "fit": "Linear",
        "fn": 119,
        "include_baseline_error": true,
        "n": 120,
        "outlier_excluded": [
            0
        ],
        "reviewed": true,
        "user_excluded": [],
        "value": 0.19463632779391482
    },
    "Ar39": {
        "error": 0.013710108869848848,
        "error_type": "SEM",
        "filter_outliers_dict": {
            "filter_outliers": true,
            "iterations": 1,
            "std_devs": 3,
            "use_iqr_filtering": false,
            "use_standard_deviation_filtering": false
        },
        "fit": "Linear",
        "fn": 118,
        "include_baseline_error": true,
        "n": 120,
        "outlier_excluded": [
            0,
            1
        ],
        "reviewed": true,
        "user_excluded": [],
        "value": 12.396988807579845
    },
    "Ar40": {
        "error": 0.10848452150080637,
        "error_type": "SEM",
        "filter_outliers_dict": {
            "filter_outliers": true,
            "iterations": 1,
            "std_devs": 3,
            "use_iqr_filtering": false,
            "use_standard_deviation_filtering": false
        },
        "fit": "Linear",
        "fn": 120,
        "include_baseline_error": true,
        "n": 120,
        "outlier_excluded": [],
        "reviewed": true,
        "user_excluded": [],
        "value": 2102.4791588716676
    },
    "Ar41": {
        "error": 0.02449499849829243,
        "error_type": "SEM",
        "filter_outliers_dict": {
            "filter_outliers": true,
            "iterations": 1,
            "std_devs": 2
        },
        "fit": "Average",
        "value": -0.39091866290870875
    }
}