{
    "AX": {
        "error": 0.006922883898934039,
        "error_type": "SEM",
        "filter_outliers_dict": {
            "filter_outliers": true,
            "iterations": 1,
            "std_devs": 2,
            "use_iqr_filtering": false,
            "use_standard_deviation_filtering": false
        },
        "fit": "Average",
        "fn": 28,
        "include_baseline_error": false,
        "n": 30,
        "outlier_excluded": [
            1,
            25
        ],
        "reviewed": true,
        "user_excluded": [],
        "value": 0.28259602189064026
    },
    "CDD": {
        "error": 3.920270280813016e-05,
        "error_type": "SEM",
        "filter_outliers_dict": {
            "filter_outliers": true,
            "iterations": 1,
            "std_devs": 10,
            "use_iqr_filtering": false,
            "use_standard_deviation_filtering": false
        },
        "fit": "Average",
        "fn": 30,
        "include_baseline_error": false,
        "n": 30,
        "outlier_excluded": [],
        "reviewed": true,
        "user_excluded": [],
        "value": 0.0003918458678526804
    },
    "H1": {
        "error": 0.009539941990836718,
        "error_type": "SEM",
        "filter_outliers_dict": {
            "filter_outliers": true,
            "iterations": 1,
            "std_devs": 2,
            "use_iqr_filtering": false,
            "use_standard_deviation_filtering": false
        },
        "fit": "Average",
        "fn": 28,
        "include_baseline_error": false,
        "n": 30,
        "outlier_excluded": [
            3,
            22
        ],
        "reviewed": true,
        "user_excluded": [],
        "value": 0.17266389541327953
    },
    "H2": {
        "error": 0.047276128186368976,
        "error_type": "SEM",
        "filter_outliers_dict": {
            "filter_outliers": true,
            "iterations": 1,
            "std_devs": 2
        },
        "fit": "average",
        "value": -0.5061431669124251
    },
    "L1": {
        "error": 0.005013877432222527,
        "error_type": "SEM",
        "filter_outliers_dict": {
            "filter_outliers": true,
            "iterations": 1,
            "std_devs": 2,
            "use_iqr_filtering": false,
            "use_standard_deviation_filtering": false
        },
        "fit": "Average",
        "fn": 29,
        "include_baseline_error": false,
        "n": 30,
        "outlier_excluded": [
            15
        ],
        "reviewed": true,
        "user_excluded": [],
        "value": 0.019122515058401842
    },
    "L2": {
        "error": 0.004132269754734507,
        "error_type": "SEM",
        "filter_outliers_dict": {
            "filter_outliers": true,
            "iterations": 1,
            "std_devs": 2,
            "use_iqr_filtering": false,
            "use_standard_deviation_filtering": false
        },
        "fit": "Average",
        "fn": 29,
        "include_baseline_error": false,
        "n": 30,
        "outlier_excluded": [
            22
        ],
        "reviewed": true,
        "user_excluded": [],
        "value": -0.04146340197245269
    }
}